nessie/__init__.py
nessie/catalog.py
nessie/core_funcs.py
nessie/cosmology.py
nessie/helper_funcs.py
nessie/optimizer.py
nessie_py-1.0.9.dist-info/METADATA
nessie_py-1.0.9.dist-info/WHEEL
nessie_py-1.0.9.dist-info/licenses/LICENSE
nessie_py.libs/libgcc_s-0366c7ba.so.1
nessie_py/__init__.py
nessie_py/nessie_py.cpython-311-arm-linux-musleabihf.so
nessie_py-1.0.9.dist-info/RECORD
