Metadata-Version: 2.4
Name: nessie_py
Version: 1.0.9
Classifier: Programming Language :: Rust
Classifier: Programming Language :: Python :: Implementation :: CPython
Classifier: Programming Language :: Python :: Implementation :: PyPy
Classifier: Programming Language :: Python :: 3
Classifier: Operating System :: MacOS
Classifier: Operating System :: POSIX :: Linux
Requires-Dist: networkx>=3.5
Requires-Dist: statsmodels>=0.14.4
Requires-Dist: scipy>=1.16.0
Requires-Dist: numpy>=2.3.1
License-File: LICENSE
Summary: A fast and flexible friends-of-friends galaxy-group finder based on Rust.
Author-email: Trystan Lambert <trystanscottlambert@gmail.com>
Requires-Python: >=3.11
